/*     */ package at.coro.client;
/*     */ 
/*     */ import at.coro.sql.SQLDriver;
/*     */ import at.coro.utils.ConfigManager;
/*     */ import java.io.PrintStream;
/*     */ import java.sql.ResultSet;
/*     */ import java.sql.ResultSetMetaData;
/*     */ import java.sql.SQLException;
/*     */ import java.util.Properties;
/*     */ import java.util.TreeMap;
/*     */ 
/*     */ 
/*     */ 
/*     */ 
/*     */ 
/*     */ 
/*     */ 
/*     */ 
/*     */ 
/*     */ 
/*     */ 
/*     */ 
/*     */ 
/*     */ 
/*     */ 
/*     */ 
/*     */ 
/*     */ 
/*     */ 
/*     */ public class SQLCli
/*     */ {
/*     */   private static final String version = "0.95a";
/*     */   private static final String cpath = "config.ini";
/*     */   private static final String info = "Java SQL Client Version 0.95a\n(c) 2015 Viktor Fuchs\n";
/*     */   protected SQLDriver sqld;
/*  36 */   private static ConfigManager cm = new ConfigManager("config.ini");
/*     */   
/*  38 */   private static Properties config = new Properties();
/*     */   
/*     */ 
/*     */ 
/*  42 */   private static TreeMap<String, String> commandList = new TreeMap();
/*  43 */   private static TreeMap<String, String> sqlCommands = new TreeMap();
/*     */   
/*     */ 
/*     */ 
/*     */ 
/*     */   private static void registerCommands()
/*     */   {
/*  50 */     commandList.put("/help", "Displays this helptext");
/*  51 */     commandList
/*  52 */       .put("/connect host username password [database]", 
/*  53 */       "Connects to new database, specify password as \"null\", if not set. Database is optional.");
/*  54 */     commandList
/*  55 */       .put("/save", 
/*  56 */       "Saves the current connection as configuration (WARNING: PASSWORD IS SAVED AS PLAIN TEXT!)");
/*  57 */     commandList
/*  58 */       .put("/script path_to_script [verbose]", 
/*  59 */       "Runs the specified script. If verbose is true, outputs the script as it is run. Optional.");
/*  60 */     commandList.put("/clear", "Resets and deletes a saved configuration");
/*  61 */     commandList.put("/exit", "Disconnects properly and quits the program");
/*     */     
/*  63 */     sqlCommands.put("SELECT", "");
/*  64 */     sqlCommands.put("SHOW", "");
/*     */   }
/*     */   
/*     */ 
/*     */ 
/*     */ 
/*     */ 
/*     */ 
/*     */ 
/*     */ 
/*     */   private static SQLDriver createConnection(Properties configuration)
/*     */     throws SQLException
/*     */   {
/*  77 */     if (config.getProperty("password").equals("null")) {
/*  78 */       config.setProperty("password", "");
/*     */     }
/*  80 */     if (config.getProperty("db") == null) {
/*  81 */       config.setProperty("db", "");
/*     */     }
/*  83 */     System.out.println("\nEstablishing connection to database " + 
/*  84 */       config.getProperty("user") + "@" + config.getProperty("host") + 
/*  85 */       "...");
/*  86 */     return new SQLDriver(config.getProperty("host"), 
/*  87 */       config.getProperty("user"), config.getProperty("password"), 
/*  88 */       config.getProperty("db"));
/*     */   }
/*     */   
/*     */ 
/*     */ 
/*     */ 
/*     */ 
/*     */ 
/*     */   private static void updateConfig(String[] credentials)
/*     */   {
/*  98 */     config.setProperty("host", credentials[0]);
/*  99 */     config.setProperty("user", credentials[1]);
/* 100 */     config.setProperty("password", credentials[2]);
/* 101 */     if (credentials.length > 3) {
/* 102 */       config.setProperty("db", credentials[3]);
/*     */     }
/*     */   }
/*     */   
/*     */ 
/*     */ 
/*     */ 
/*     */ 
/*     */ 
/*     */   private static void listResults(ResultSet rs)
/*     */     throws SQLException
/*     */   {
/* 114 */     int rc = 0;
/* 115 */     for (int i = 1; i <= rs.getMetaData().getColumnCount(); i++) {
/* 116 */       System.out.print(rs.getMetaData().getColumnLabel(i));
/* 117 */       if (i < rs.getMetaData().getColumnCount()) {
/* 118 */         System.out.print("\t|\t");
/*     */       }
/*     */     }
/* 121 */     System.out.println();
/* 122 */     while (rs.next()) {
/* 123 */       rc++;
/* 124 */       for (int i = 1; i <= rs.getMetaData().getColumnCount(); i++) {
/* 125 */         System.out.print(rs.getObject(i));
/* 126 */         if (i < rs.getMetaData().getColumnCount()) {
/* 127 */           System.out.print("\t|\t");
/*     */         }
/*     */       }
/* 130 */       System.out.println();
/*     */     }
/* 132 */     System.out.println(rc + " rows selected");
/*     */   }
/*     */   
/*     */   /* Error */
/*     */   public static void main(String[] args)
/*     */   {
/*     */     // Byte code:
/*     */     //   0: getstatic 116	java/lang/System:out	Ljava/io/PrintStream;
/*     */     //   3: ldc 14
/*     */     //   5: invokevirtual 143	java/io/PrintStream:println	(Ljava/lang/String;)V
/*     */     //   8: new 1	at/coro/client/SQLCli
/*     */     //   11: dup
/*     */     //   12: invokespecial 206	at/coro/client/SQLCli:<init>	()V
/*     */     //   15: astore_1
/*     */     //   16: new 207	java/io/BufferedReader
/*     */     //   19: dup
/*     */     //   20: new 209	java/io/InputStreamReader
/*     */     //   23: dup
/*     */     //   24: getstatic 211	java/lang/System:in	Ljava/io/InputStream;
/*     */     //   27: invokespecial 215	java/io/InputStreamReader:<init>	(Ljava/io/InputStream;)V
/*     */     //   30: invokespecial 218	java/io/BufferedReader:<init>	(Ljava/io/Reader;)V
/*     */     //   33: astore_2
/*     */     //   34: invokestatic 221	at/coro/client/SQLCli:registerCommands	()V
/*     */     //   37: aload_0
/*     */     //   38: arraylength
/*     */     //   39: iconst_1
/*     */     //   40: if_icmpge +70 -> 110
/*     */     //   43: getstatic 36	at/coro/client/SQLCli:cm	Lat/coro/utils/ConfigManager;
/*     */     //   46: invokevirtual 223	at/coro/utils/ConfigManager:configExists	()Z
/*     */     //   49: ifeq +23 -> 72
/*     */     //   52: getstatic 116	java/lang/System:out	Ljava/io/PrintStream;
/*     */     //   55: ldc -30
/*     */     //   57: invokevirtual 143	java/io/PrintStream:println	(Ljava/lang/String;)V
/*     */     //   60: getstatic 36	at/coro/client/SQLCli:cm	Lat/coro/utils/ConfigManager;
/*     */     //   63: invokevirtual 228	at/coro/utils/ConfigManager:loadConfig	()Ljava/util/Properties;
/*     */     //   66: putstatic 42	at/coro/client/SQLCli:config	Ljava/util/Properties;
/*     */     //   69: goto +41 -> 110
/*     */     //   72: getstatic 116	java/lang/System:out	Ljava/io/PrintStream;
/*     */     //   75: ldc -24
/*     */     //   77: invokevirtual 143	java/io/PrintStream:println	(Ljava/lang/String;)V
/*     */     //   80: aload_2
/*     */     //   81: invokevirtual 234	java/io/BufferedReader:readLine	()Ljava/lang/String;
/*     */     //   84: ldc -19
/*     */     //   86: invokevirtual 239	java/lang/String:split	(Ljava/lang/String;)[Ljava/lang/String;
/*     */     //   89: astore_3
/*     */     //   90: aload_3
/*     */     //   91: arraylength
/*     */     //   92: iconst_3
/*     */     //   93: if_icmpge +13 -> 106
/*     */     //   96: new 94	java/sql/SQLException
/*     */     //   99: dup
/*     */     //   100: ldc -13
/*     */     //   102: invokespecial 245	java/sql/SQLException:<init>	(Ljava/lang/String;)V
/*     */     //   105: athrow
/*     */     //   106: aload_3
/*     */     //   107: invokestatic 246	at/coro/client/SQLCli:updateConfig	([Ljava/lang/String;)V
/*     */     //   110: aload_1
/*     */     //   111: getstatic 42	at/coro/client/SQLCli:config	Ljava/util/Properties;
/*     */     //   114: invokestatic 248	at/coro/client/SQLCli:createConnection	(Ljava/util/Properties;)Lat/coro/sql/SQLDriver;
/*     */     //   117: putfield 250	at/coro/client/SQLCli:sqld	Lat/coro/sql/SQLDriver;
/*     */     //   120: goto +131 -> 251
/*     */     //   123: astore_3
/*     */     //   124: getstatic 252	java/lang/System:err	Ljava/io/PrintStream;
/*     */     //   127: ldc -1
/*     */     //   129: invokevirtual 143	java/io/PrintStream:println	(Ljava/lang/String;)V
/*     */     //   132: getstatic 252	java/lang/System:err	Ljava/io/PrintStream;
/*     */     //   135: new 122	java/lang/StringBuilder
/*     */     //   138: dup
/*     */     //   139: ldc_w 257
/*     */     //   142: invokespecial 126	java/lang/StringBuilder:<init>	(Ljava/lang/String;)V
/*     */     //   145: aload_3
/*     */     //   146: invokevirtual 259	java/sql/SQLException:getMessage	()Ljava/lang/String;
/*     */     //   149: invokevirtual 129	java/lang/StringBuilder:append	(Ljava/lang/String;)Ljava/lang/StringBuilder;
/*     */     //   152: invokevirtual 139	java/lang/StringBuilder:toString	()Ljava/lang/String;
/*     */     //   155: invokevirtual 143	java/io/PrintStream:println	(Ljava/lang/String;)V
/*     */     //   158: getstatic 36	at/coro/client/SQLCli:cm	Lat/coro/utils/ConfigManager;
/*     */     //   161: invokevirtual 223	at/coro/utils/ConfigManager:configExists	()Z
/*     */     //   164: ifeq +75 -> 239
/*     */     //   167: ldc2_w 262
/*     */     //   170: invokestatic 264	java/lang/Thread:sleep	(J)V
/*     */     //   173: goto +10 -> 183
/*     */     //   176: astore 4
/*     */     //   178: aload 4
/*     */     //   180: invokevirtual 270	java/lang/InterruptedException:printStackTrace	()V
/*     */     //   183: getstatic 116	java/lang/System:out	Ljava/io/PrintStream;
/*     */     //   186: ldc_w 275
/*     */     //   189: invokevirtual 143	java/io/PrintStream:println	(Ljava/lang/String;)V
/*     */     //   192: aload_2
/*     */     //   193: invokevirtual 234	java/io/BufferedReader:readLine	()Ljava/lang/String;
/*     */     //   196: ldc_w 277
/*     */     //   199: invokevirtual 279	java/lang/String:equalsIgnoreCase	(Ljava/lang/String;)Z
/*     */     //   202: ifeq +37 -> 239
/*     */     //   205: getstatic 116	java/lang/System:out	Ljava/io/PrintStream;
/*     */     //   208: ldc_w 283
/*     */     //   211: invokevirtual 143	java/io/PrintStream:println	(Ljava/lang/String;)V
/*     */     //   214: getstatic 36	at/coro/client/SQLCli:cm	Lat/coro/utils/ConfigManager;
/*     */     //   217: invokevirtual 285	at/coro/utils/ConfigManager:deleteConfig	()V
/*     */     //   220: goto +19 -> 239
/*     */     //   223: astore 4
/*     */     //   225: getstatic 252	java/lang/System:err	Ljava/io/PrintStream;
/*     */     //   228: ldc_w 288
/*     */     //   231: invokevirtual 143	java/io/PrintStream:println	(Ljava/lang/String;)V
/*     */     //   234: aload 4
/*     */     //   236: invokevirtual 290	java/io/IOException:printStackTrace	()V
/*     */     //   239: iconst_0
/*     */     //   240: invokestatic 293	java/lang/System:exit	(I)V
/*     */     //   243: goto +8 -> 251
/*     */     //   246: astore_3
/*     */     //   247: aload_3
/*     */     //   248: invokevirtual 290	java/io/IOException:printStackTrace	()V
/*     */     //   251: getstatic 116	java/lang/System:out	Ljava/io/PrintStream;
/*     */     //   254: ldc_w 297
/*     */     //   257: invokevirtual 173	java/io/PrintStream:print	(Ljava/lang/String;)V
/*     */     //   260: aload_1
/*     */     //   261: getfield 250	at/coro/client/SQLCli:sqld	Lat/coro/sql/SQLDriver;
/*     */     //   264: invokevirtual 299	at/coro/sql/SQLDriver:getDatabase	()Ljava/sql/ResultSet;
/*     */     //   267: astore_3
/*     */     //   268: aload_3
/*     */     //   269: invokeinterface 303 1 0
/*     */     //   274: pop
/*     */     //   275: aload_3
/*     */     //   276: iconst_1
/*     */     //   277: invokeinterface 306 2 0
/*     */     //   282: ifnull +15 -> 297
/*     */     //   285: aload_3
/*     */     //   286: iconst_1
/*     */     //   287: invokeinterface 306 2 0
/*     */     //   292: ldc 102
/*     */     //   294: if_acmpne +15 -> 309
/*     */     //   297: getstatic 116	java/lang/System:out	Ljava/io/PrintStream;
/*     */     //   300: ldc_w 309
/*     */     //   303: invokevirtual 143	java/io/PrintStream:println	(Ljava/lang/String;)V
/*     */     //   306: goto +32 -> 338
/*     */     //   309: getstatic 42	at/coro/client/SQLCli:config	Ljava/util/Properties;
/*     */     //   312: ldc 114
/*     */     //   314: aload_3
/*     */     //   315: iconst_1
/*     */     //   316: invokeinterface 306 2 0
/*     */     //   321: invokevirtual 110	java/util/Properties:setProperty	(Ljava/lang/String;Ljava/lang/String;)Ljava/lang/Object;
/*     */     //   324: pop
/*     */     //   325: getstatic 116	java/lang/System:out	Ljava/io/PrintStream;
/*     */     //   328: aload_3
/*     */     //   329: iconst_1
/*     */     //   330: invokeinterface 306 2 0
/*     */     //   335: invokevirtual 143	java/io/PrintStream:println	(Ljava/lang/String;)V
/*     */     //   338: getstatic 116	java/lang/System:out	Ljava/io/PrintStream;
/*     */     //   341: ldc_w 311
/*     */     //   344: invokevirtual 143	java/io/PrintStream:println	(Ljava/lang/String;)V
/*     */     //   347: getstatic 116	java/lang/System:out	Ljava/io/PrintStream;
/*     */     //   350: ldc_w 313
/*     */     //   353: invokevirtual 173	java/io/PrintStream:print	(Ljava/lang/String;)V
/*     */     //   356: aload_2
/*     */     //   357: invokevirtual 234	java/io/BufferedReader:readLine	()Ljava/lang/String;
/*     */     //   360: astore 4
/*     */     //   362: aload 4
/*     */     //   364: invokevirtual 315	java/lang/String:isEmpty	()Z
/*     */     //   367: ifne -20 -> 347
/*     */     //   370: getstatic 116	java/lang/System:out	Ljava/io/PrintStream;
/*     */     //   373: invokevirtual 182	java/io/PrintStream:println	()V
/*     */     //   376: aload 4
/*     */     //   378: invokevirtual 318	java/lang/String:toUpperCase	()Ljava/lang/String;
/*     */     //   381: ldc_w 321
/*     */     //   384: invokevirtual 323	java/lang/String:startsWith	(Ljava/lang/String;)Z
/*     */     //   387: ifeq +112 -> 499
/*     */     //   390: getstatic 116	java/lang/System:out	Ljava/io/PrintStream;
/*     */     //   393: ldc 14
/*     */     //   395: invokevirtual 143	java/io/PrintStream:println	(Ljava/lang/String;)V
/*     */     //   398: getstatic 116	java/lang/System:out	Ljava/io/PrintStream;
/*     */     //   401: ldc_w 326
/*     */     //   404: invokevirtual 143	java/io/PrintStream:println	(Ljava/lang/String;)V
/*     */     //   407: getstatic 47	at/coro/client/SQLCli:commandList	Ljava/util/TreeMap;
/*     */     //   410: invokevirtual 328	java/util/TreeMap:entrySet	()Ljava/util/Set;
/*     */     //   413: invokeinterface 332 1 0
/*     */     //   418: astore 6
/*     */     //   420: goto +66 -> 486
/*     */     //   423: aload 6
/*     */     //   425: invokeinterface 338 1 0
/*     */     //   430: checkcast 343	java/util/Map$Entry
/*     */     //   433: astore 5
/*     */     //   435: getstatic 116	java/lang/System:out	Ljava/io/PrintStream;
/*     */     //   438: new 122	java/lang/StringBuilder
/*     */     //   441: dup
/*     */     //   442: ldc_w 313
/*     */     //   445: invokespecial 126	java/lang/StringBuilder:<init>	(Ljava/lang/String;)V
/*     */     //   448: aload 5
/*     */     //   450: invokeinterface 345 1 0
/*     */     //   455: checkcast 105	java/lang/String
/*     */     //   458: invokevirtual 129	java/lang/StringBuilder:append	(Ljava/lang/String;)Ljava/lang/StringBuilder;
/*     */     //   461: ldc_w 348
/*     */     //   464: invokevirtual 129	java/lang/StringBuilder:append	(Ljava/lang/String;)Ljava/lang/StringBuilder;
/*     */     //   467: aload 5
/*     */     //   469: invokeinterface 350 1 0
/*     */     //   474: checkcast 105	java/lang/String
/*     */     //   477: invokevirtual 129	java/lang/StringBuilder:append	(Ljava/lang/String;)Ljava/lang/StringBuilder;
/*     */     //   480: invokevirtual 139	java/lang/StringBuilder:toString	()Ljava/lang/String;
/*     */     //   483: invokevirtual 143	java/io/PrintStream:println	(Ljava/lang/String;)V
/*     */     //   486: aload 6
/*     */     //   488: invokeinterface 353 1 0
/*     */     //   493: ifne -70 -> 423
/*     */     //   496: goto +659 -> 1155
/*     */     //   499: aload 4
/*     */     //   501: invokevirtual 318	java/lang/String:toUpperCase	()Ljava/lang/String;
/*     */     //   504: ldc_w 356
/*     */     //   507: invokevirtual 323	java/lang/String:startsWith	(Ljava/lang/String;)Z
/*     */     //   510: ifeq +119 -> 629
/*     */     //   513: aload 4
/*     */     //   515: aload 4
/*     */     //   517: ldc -19
/*     */     //   519: invokevirtual 358	java/lang/String:indexOf	(Ljava/lang/String;)I
/*     */     //   522: iconst_1
/*     */     //   523: iadd
/*     */     //   524: invokevirtual 362	java/lang/String:substring	(I)Ljava/lang/String;
/*     */     //   527: ldc -19
/*     */     //   529: invokevirtual 239	java/lang/String:split	(Ljava/lang/String;)[Ljava/lang/String;
/*     */     //   532: astore 5
/*     */     //   534: aload 5
/*     */     //   536: arraylength
/*     */     //   537: iconst_3
/*     */     //   538: if_icmpge +13 -> 551
/*     */     //   541: new 94	java/sql/SQLException
/*     */     //   544: dup
/*     */     //   545: ldc -13
/*     */     //   547: invokespecial 245	java/sql/SQLException:<init>	(Ljava/lang/String;)V
/*     */     //   550: athrow
/*     */     //   551: getstatic 116	java/lang/System:out	Ljava/io/PrintStream;
/*     */     //   554: ldc_w 365
/*     */     //   557: invokevirtual 143	java/io/PrintStream:println	(Ljava/lang/String;)V
/*     */     //   560: aload_1
/*     */     //   561: getfield 250	at/coro/client/SQLCli:sqld	Lat/coro/sql/SQLDriver;
/*     */     //   564: invokevirtual 367	at/coro/sql/SQLDriver:disconnect	()V
/*     */     //   567: aload 5
/*     */     //   569: invokestatic 246	at/coro/client/SQLCli:updateConfig	([Ljava/lang/String;)V
/*     */     //   572: aload_1
/*     */     //   573: getstatic 42	at/coro/client/SQLCli:config	Ljava/util/Properties;
/*     */     //   576: invokestatic 248	at/coro/client/SQLCli:createConnection	(Ljava/util/Properties;)Lat/coro/sql/SQLDriver;
/*     */     //   579: putfield 250	at/coro/client/SQLCli:sqld	Lat/coro/sql/SQLDriver;
/*     */     //   582: goto +573 -> 1155
/*     */     //   585: astore 5
/*     */     //   587: getstatic 252	java/lang/System:err	Ljava/io/PrintStream;
/*     */     //   590: ldc -1
/*     */     //   592: invokevirtual 143	java/io/PrintStream:println	(Ljava/lang/String;)V
/*     */     //   595: getstatic 252	java/lang/System:err	Ljava/io/PrintStream;
/*     */     //   598: new 122	java/lang/StringBuilder
/*     */     //   601: dup
/*     */     //   602: ldc_w 257
/*     */     //   605: invokespecial 126	java/lang/StringBuilder:<init>	(Ljava/lang/String;)V
/*     */     //   608: aload 5
/*     */     //   610: invokevirtual 259	java/sql/SQLException:getMessage	()Ljava/lang/String;
/*     */     //   613: invokevirtual 129	java/lang/StringBuilder:append	(Ljava/lang/String;)Ljava/lang/StringBuilder;
/*     */     //   616: invokevirtual 139	java/lang/StringBuilder:toString	()Ljava/lang/String;
/*     */     //   619: invokevirtual 143	java/io/PrintStream:println	(Ljava/lang/String;)V
/*     */     //   622: iconst_0
/*     */     //   623: invokestatic 293	java/lang/System:exit	(I)V
/*     */     //   626: goto +529 -> 1155
/*     */     //   629: aload 4
/*     */     //   631: invokevirtual 318	java/lang/String:toUpperCase	()Ljava/lang/String;
/*     */     //   634: ldc_w 370
/*     */     //   637: invokevirtual 323	java/lang/String:startsWith	(Ljava/lang/String;)Z
/*     */     //   640: ifeq +198 -> 838
/*     */     //   643: ldc 87
/*     */     //   645: astore 6
/*     */     //   647: aload 4
/*     */     //   649: aload 4
/*     */     //   651: ldc -19
/*     */     //   653: invokevirtual 358	java/lang/String:indexOf	(Ljava/lang/String;)I
/*     */     //   656: iconst_1
/*     */     //   657: iadd
/*     */     //   658: invokevirtual 362	java/lang/String:substring	(I)Ljava/lang/String;
/*     */     //   661: ldc -19
/*     */     //   663: invokevirtual 239	java/lang/String:split	(Ljava/lang/String;)[Ljava/lang/String;
/*     */     //   666: astore 7
/*     */     //   668: new 207	java/io/BufferedReader
/*     */     //   671: dup
/*     */     //   672: new 372	java/io/FileReader
/*     */     //   675: dup
/*     */     //   676: aload 7
/*     */     //   678: iconst_0
/*     */     //   679: aaload
/*     */     //   680: invokespecial 374	java/io/FileReader:<init>	(Ljava/lang/String;)V
/*     */     //   683: invokespecial 218	java/io/BufferedReader:<init>	(Ljava/io/Reader;)V
/*     */     //   686: astore 8
/*     */     //   688: getstatic 116	java/lang/System:out	Ljava/io/PrintStream;
/*     */     //   691: new 122	java/lang/StringBuilder
/*     */     //   694: dup
/*     */     //   695: ldc_w 375
/*     */     //   698: invokespecial 126	java/lang/StringBuilder:<init>	(Ljava/lang/String;)V
/*     */     //   701: aload 7
/*     */     //   703: iconst_0
/*     */     //   704: aaload
/*     */     //   705: invokevirtual 129	java/lang/StringBuilder:append	(Ljava/lang/String;)Ljava/lang/StringBuilder;
/*     */     //   708: ldc -119
/*     */     //   710: invokevirtual 129	java/lang/StringBuilder:append	(Ljava/lang/String;)Ljava/lang/StringBuilder;
/*     */     //   713: invokevirtual 139	java/lang/StringBuilder:toString	()Ljava/lang/String;
/*     */     //   716: invokevirtual 143	java/io/PrintStream:println	(Ljava/lang/String;)V
/*     */     //   719: goto +100 -> 819
/*     */     //   722: aload 5
/*     */     //   724: ldc_w 377
/*     */     //   727: invokevirtual 323	java/lang/String:startsWith	(Ljava/lang/String;)Z
/*     */     //   730: ifne +89 -> 819
/*     */     //   733: new 122	java/lang/StringBuilder
/*     */     //   736: dup
/*     */     //   737: aload 6
/*     */     //   739: invokestatic 379	java/lang/String:valueOf	(Ljava/lang/Object;)Ljava/lang/String;
/*     */     //   742: invokespecial 126	java/lang/StringBuilder:<init>	(Ljava/lang/String;)V
/*     */     //   745: aload 5
/*     */     //   747: invokevirtual 129	java/lang/StringBuilder:append	(Ljava/lang/String;)Ljava/lang/StringBuilder;
/*     */     //   750: invokevirtual 139	java/lang/StringBuilder:toString	()Ljava/lang/String;
/*     */     //   753: astore 6
/*     */     //   755: aload 7
/*     */     //   757: arraylength
/*     */     //   758: iconst_1
/*     */     //   759: if_icmple +24 -> 783
/*     */     //   762: aload 7
/*     */     //   764: iconst_1
/*     */     //   765: aaload
/*     */     //   766: ldc_w 382
/*     */     //   769: invokevirtual 279	java/lang/String:equalsIgnoreCase	(Ljava/lang/String;)Z
/*     */     //   772: ifeq +11 -> 783
/*     */     //   775: getstatic 116	java/lang/System:out	Ljava/io/PrintStream;
/*     */     //   778: aload 5
/*     */     //   780: invokevirtual 143	java/io/PrintStream:println	(Ljava/lang/String;)V
/*     */     //   783: aload 5
/*     */     //   785: ldc_w 384
/*     */     //   788: invokevirtual 386	java/lang/String:endsWith	(Ljava/lang/String;)Z
/*     */     //   791: ifeq +28 -> 819
/*     */     //   794: aload_1
/*     */     //   795: getfield 250	at/coro/client/SQLCli:sqld	Lat/coro/sql/SQLDriver;
/*     */     //   798: aload 6
/*     */     //   800: invokevirtual 389	at/coro/sql/SQLDriver:autoExecute	(Ljava/lang/String;)Ljava/sql/ResultSet;
/*     */     //   803: astore 9
/*     */     //   805: ldc 87
/*     */     //   807: astore 6
/*     */     //   809: aload 9
/*     */     //   811: ifnull +8 -> 819
/*     */     //   814: aload 9
/*     */     //   816: invokestatic 393	at/coro/client/SQLCli:listResults	(Ljava/sql/ResultSet;)V
/*     */     //   819: aload 8
/*     */     //   821: invokevirtual 234	java/io/BufferedReader:readLine	()Ljava/lang/String;
/*     */     //   824: dup
/*     */     //   825: astore 5
/*     */     //   827: ifnonnull -105 -> 722
/*     */     //   830: aload 8
/*     */     //   832: invokevirtual 395	java/io/BufferedReader:close	()V
/*     */     //   835: goto +320 -> 1155
/*     */     //   838: aload 4
/*     */     //   840: invokevirtual 318	java/lang/String:toUpperCase	()Ljava/lang/String;
/*     */     //   843: ldc_w 398
/*     */     //   846: invokevirtual 323	java/lang/String:startsWith	(Ljava/lang/String;)Z
/*     */     //   849: ifeq +42 -> 891
/*     */     //   852: getstatic 116	java/lang/System:out	Ljava/io/PrintStream;
/*     */     //   855: ldc_w 400
/*     */     //   858: invokevirtual 143	java/io/PrintStream:println	(Ljava/lang/String;)V
/*     */     //   861: getstatic 116	java/lang/System:out	Ljava/io/PrintStream;
/*     */     //   864: ldc_w 402
/*     */     //   867: invokevirtual 143	java/io/PrintStream:println	(Ljava/lang/String;)V
/*     */     //   870: getstatic 36	at/coro/client/SQLCli:cm	Lat/coro/utils/ConfigManager;
/*     */     //   873: getstatic 42	at/coro/client/SQLCli:config	Ljava/util/Properties;
/*     */     //   876: invokevirtual 404	at/coro/utils/ConfigManager:saveConfig	(Ljava/util/Properties;)V
/*     */     //   879: getstatic 116	java/lang/System:out	Ljava/io/PrintStream;
/*     */     //   882: ldc_w 408
/*     */     //   885: invokevirtual 143	java/io/PrintStream:println	(Ljava/lang/String;)V
/*     */     //   888: goto +267 -> 1155
/*     */     //   891: aload 4
/*     */     //   893: invokevirtual 318	java/lang/String:toUpperCase	()Ljava/lang/String;
/*     */     //   896: ldc_w 410
/*     */     //   899: invokevirtual 323	java/lang/String:startsWith	(Ljava/lang/String;)Z
/*     */     //   902: ifeq +42 -> 944
/*     */     //   905: getstatic 36	at/coro/client/SQLCli:cm	Lat/coro/utils/ConfigManager;
/*     */     //   908: invokevirtual 223	at/coro/utils/ConfigManager:configExists	()Z
/*     */     //   911: ifeq +21 -> 932
/*     */     //   914: getstatic 36	at/coro/client/SQLCli:cm	Lat/coro/utils/ConfigManager;
/*     */     //   917: invokevirtual 285	at/coro/utils/ConfigManager:deleteConfig	()V
/*     */     //   920: getstatic 116	java/lang/System:out	Ljava/io/PrintStream;
/*     */     //   923: ldc_w 412
/*     */     //   926: invokevirtual 143	java/io/PrintStream:println	(Ljava/lang/String;)V
/*     */     //   929: goto +226 -> 1155
/*     */     //   932: getstatic 116	java/lang/System:out	Ljava/io/PrintStream;
/*     */     //   935: ldc_w 414
/*     */     //   938: invokevirtual 143	java/io/PrintStream:println	(Ljava/lang/String;)V
/*     */     //   941: goto +214 -> 1155
/*     */     //   944: aload 4
/*     */     //   946: invokevirtual 318	java/lang/String:toUpperCase	()Ljava/lang/String;
/*     */     //   949: ldc_w 416
/*     */     //   952: invokevirtual 323	java/lang/String:startsWith	(Ljava/lang/String;)Z
/*     */     //   955: ifeq +26 -> 981
/*     */     //   958: getstatic 116	java/lang/System:out	Ljava/io/PrintStream;
/*     */     //   961: ldc_w 418
/*     */     //   964: invokevirtual 143	java/io/PrintStream:println	(Ljava/lang/String;)V
/*     */     //   967: aload_1
/*     */     //   968: getfield 250	at/coro/client/SQLCli:sqld	Lat/coro/sql/SQLDriver;
/*     */     //   971: invokevirtual 367	at/coro/sql/SQLDriver:disconnect	()V
/*     */     //   974: iconst_0
/*     */     //   975: invokestatic 293	java/lang/System:exit	(I)V
/*     */     //   978: goto +177 -> 1155
/*     */     //   981: aload 4
/*     */     //   983: invokevirtual 318	java/lang/String:toUpperCase	()Ljava/lang/String;
/*     */     //   986: ldc 85
/*     */     //   988: invokevirtual 323	java/lang/String:startsWith	(Ljava/lang/String;)Z
/*     */     //   991: ifne +16 -> 1007
/*     */     //   994: aload 4
/*     */     //   996: invokevirtual 318	java/lang/String:toUpperCase	()Ljava/lang/String;
/*     */     //   999: ldc 89
/*     */     //   1001: invokevirtual 323	java/lang/String:startsWith	(Ljava/lang/String;)Z
/*     */     //   1004: ifeq +22 -> 1026
/*     */     //   1007: aload_1
/*     */     //   1008: getfield 250	at/coro/client/SQLCli:sqld	Lat/coro/sql/SQLDriver;
/*     */     //   1011: aload 4
/*     */     //   1013: invokevirtual 420	at/coro/sql/SQLDriver:executeQuery	(Ljava/lang/String;)Ljava/sql/ResultSet;
/*     */     //   1016: astore 5
/*     */     //   1018: aload 5
/*     */     //   1020: invokestatic 393	at/coro/client/SQLCli:listResults	(Ljava/sql/ResultSet;)V
/*     */     //   1023: goto +132 -> 1155
/*     */     //   1026: aload_1
/*     */     //   1027: getfield 250	at/coro/client/SQLCli:sqld	Lat/coro/sql/SQLDriver;
/*     */     //   1030: aload 4
/*     */     //   1032: invokevirtual 423	at/coro/sql/SQLDriver:execute	(Ljava/lang/String;)Z
/*     */     //   1035: pop
/*     */     //   1036: goto +119 -> 1155
/*     */     //   1039: astore_3
/*     */     //   1040: getstatic 252	java/lang/System:err	Ljava/io/PrintStream;
/*     */     //   1043: ldc_w 426
/*     */     //   1046: invokevirtual 143	java/io/PrintStream:println	(Ljava/lang/String;)V
/*     */     //   1049: getstatic 252	java/lang/System:err	Ljava/io/PrintStream;
/*     */     //   1052: new 122	java/lang/StringBuilder
/*     */     //   1055: dup
/*     */     //   1056: ldc_w 257
/*     */     //   1059: invokespecial 126	java/lang/StringBuilder:<init>	(Ljava/lang/String;)V
/*     */     //   1062: aload_3
/*     */     //   1063: invokevirtual 428	java/io/IOException:getMessage	()Ljava/lang/String;
/*     */     //   1066: invokevirtual 129	java/lang/StringBuilder:append	(Ljava/lang/String;)Ljava/lang/StringBuilder;
/*     */     //   1069: invokevirtual 139	java/lang/StringBuilder:toString	()Ljava/lang/String;
/*     */     //   1072: invokevirtual 143	java/io/PrintStream:println	(Ljava/lang/String;)V
/*     */     //   1075: ldc2_w 429
/*     */     //   1078: invokestatic 264	java/lang/Thread:sleep	(J)V
/*     */     //   1081: goto +85 -> 1166
/*     */     //   1084: astore 11
/*     */     //   1086: goto +80 -> 1166
/*     */     //   1089: astore_3
/*     */     //   1090: getstatic 252	java/lang/System:err	Ljava/io/PrintStream;
/*     */     //   1093: ldc_w 431
/*     */     //   1096: invokevirtual 143	java/io/PrintStream:println	(Ljava/lang/String;)V
/*     */     //   1099: getstatic 252	java/lang/System:err	Ljava/io/PrintStream;
/*     */     //   1102: new 122	java/lang/StringBuilder
/*     */     //   1105: dup
/*     */     //   1106: ldc_w 257
/*     */     //   1109: invokespecial 126	java/lang/StringBuilder:<init>	(Ljava/lang/String;)V
/*     */     //   1112: aload_3
/*     */     //   1113: invokevirtual 259	java/sql/SQLException:getMessage	()Ljava/lang/String;
/*     */     //   1116: invokevirtual 129	java/lang/StringBuilder:append	(Ljava/lang/String;)Ljava/lang/StringBuilder;
/*     */     //   1119: invokevirtual 139	java/lang/StringBuilder:toString	()Ljava/lang/String;
/*     */     //   1122: invokevirtual 143	java/io/PrintStream:println	(Ljava/lang/String;)V
/*     */     //   1125: ldc2_w 429
/*     */     //   1128: invokestatic 264	java/lang/Thread:sleep	(J)V
/*     */     //   1131: goto +35 -> 1166
/*     */     //   1134: astore 11
/*     */     //   1136: goto +30 -> 1166
/*     */     //   1139: astore 10
/*     */     //   1141: ldc2_w 429
/*     */     //   1144: invokestatic 264	java/lang/Thread:sleep	(J)V
/*     */     //   1147: goto +5 -> 1152
/*     */     //   1150: astore 11
/*     */     //   1152: aload 10
/*     */     //   1154: athrow
/*     */     //   1155: ldc2_w 429
/*     */     //   1158: invokestatic 264	java/lang/Thread:sleep	(J)V
/*     */     //   1161: goto +5 -> 1166
/*     */     //   1164: astore 11
/*     */     //   1166: getstatic 116	java/lang/System:out	Ljava/io/PrintStream;
/*     */     //   1169: invokevirtual 182	java/io/PrintStream:println	()V
/*     */     //   1172: goto -921 -> 251
/*     */     // Line number table:
/*     */     //   Java source line #141	-> byte code offset #0
/*     */     //   Java source line #143	-> byte code offset #8
/*     */     //   Java source line #144	-> byte code offset #16
/*     */     //   Java source line #146	-> byte code offset #34
/*     */     //   Java source line #149	-> byte code offset #37
/*     */     //   Java source line #150	-> byte code offset #43
/*     */     //   Java source line #151	-> byte code offset #52
/*     */     //   Java source line #152	-> byte code offset #55
/*     */     //   Java source line #153	-> byte code offset #60
/*     */     //   Java source line #154	-> byte code offset #69
/*     */     //   Java source line #155	-> byte code offset #72
/*     */     //   Java source line #156	-> byte code offset #75
/*     */     //   Java source line #157	-> byte code offset #80
/*     */     //   Java source line #158	-> byte code offset #90
/*     */     //   Java source line #159	-> byte code offset #96
/*     */     //   Java source line #161	-> byte code offset #106
/*     */     //   Java source line #165	-> byte code offset #110
/*     */     //   Java source line #166	-> byte code offset #120
/*     */     //   Java source line #167	-> byte code offset #124
/*     */     //   Java source line #168	-> byte code offset #127
/*     */     //   Java source line #169	-> byte code offset #132
/*     */     //   Java source line #170	-> byte code offset #158
/*     */     //   Java source line #172	-> byte code offset #167
/*     */     //   Java source line #173	-> byte code offset #173
/*     */     //   Java source line #174	-> byte code offset #178
/*     */     //   Java source line #176	-> byte code offset #183
/*     */     //   Java source line #177	-> byte code offset #186
/*     */     //   Java source line #179	-> byte code offset #192
/*     */     //   Java source line #180	-> byte code offset #205
/*     */     //   Java source line #181	-> byte code offset #214
/*     */     //   Java source line #183	-> byte code offset #220
/*     */     //   Java source line #184	-> byte code offset #225
/*     */     //   Java source line #185	-> byte code offset #234
/*     */     //   Java source line #189	-> byte code offset #239
/*     */     //   Java source line #190	-> byte code offset #246
/*     */     //   Java source line #191	-> byte code offset #247
/*     */     //   Java source line #195	-> byte code offset #251
/*     */     //   Java source line #196	-> byte code offset #260
/*     */     //   Java source line #197	-> byte code offset #268
/*     */     //   Java source line #198	-> byte code offset #275
/*     */     //   Java source line #199	-> byte code offset #285
/*     */     //   Java source line #200	-> byte code offset #297
/*     */     //   Java source line #201	-> byte code offset #306
/*     */     //   Java source line #202	-> byte code offset #309
/*     */     //   Java source line #203	-> byte code offset #325
/*     */     //   Java source line #206	-> byte code offset #338
/*     */     //   Java source line #207	-> byte code offset #341
/*     */     //   Java source line #210	-> byte code offset #347
/*     */     //   Java source line #211	-> byte code offset #356
/*     */     //   Java source line #212	-> byte code offset #362
/*     */     //   Java source line #213	-> byte code offset #370
/*     */     //   Java source line #214	-> byte code offset #376
/*     */     //   Java source line #215	-> byte code offset #390
/*     */     //   Java source line #216	-> byte code offset #398
/*     */     //   Java source line #217	-> byte code offset #407
/*     */     //   Java source line #218	-> byte code offset #435
/*     */     //   Java source line #219	-> byte code offset #467
/*     */     //   Java source line #218	-> byte code offset #483
/*     */     //   Java source line #217	-> byte code offset #486
/*     */     //   Java source line #221	-> byte code offset #496
/*     */     //   Java source line #223	-> byte code offset #513
/*     */     //   Java source line #224	-> byte code offset #515
/*     */     //   Java source line #223	-> byte code offset #524
/*     */     //   Java source line #224	-> byte code offset #527
/*     */     //   Java source line #223	-> byte code offset #532
/*     */     //   Java source line #225	-> byte code offset #534
/*     */     //   Java source line #226	-> byte code offset #541
/*     */     //   Java source line #228	-> byte code offset #551
/*     */     //   Java source line #229	-> byte code offset #560
/*     */     //   Java source line #230	-> byte code offset #567
/*     */     //   Java source line #231	-> byte code offset #572
/*     */     //   Java source line #232	-> byte code offset #582
/*     */     //   Java source line #233	-> byte code offset #587
/*     */     //   Java source line #234	-> byte code offset #590
/*     */     //   Java source line #235	-> byte code offset #595
/*     */     //   Java source line #236	-> byte code offset #622
/*     */     //   Java source line #238	-> byte code offset #626
/*     */     //   Java source line #240	-> byte code offset #643
/*     */     //   Java source line #241	-> byte code offset #647
/*     */     //   Java source line #242	-> byte code offset #661
/*     */     //   Java source line #241	-> byte code offset #663
/*     */     //   Java source line #243	-> byte code offset #668
/*     */     //   Java source line #244	-> byte code offset #676
/*     */     //   Java source line #243	-> byte code offset #683
/*     */     //   Java source line #245	-> byte code offset #688
/*     */     //   Java source line #246	-> byte code offset #719
/*     */     //   Java source line #247	-> byte code offset #722
/*     */     //   Java source line #248	-> byte code offset #733
/*     */     //   Java source line #249	-> byte code offset #755
/*     */     //   Java source line #250	-> byte code offset #762
/*     */     //   Java source line #251	-> byte code offset #775
/*     */     //   Java source line #253	-> byte code offset #783
/*     */     //   Java source line #254	-> byte code offset #794
/*     */     //   Java source line #255	-> byte code offset #805
/*     */     //   Java source line #256	-> byte code offset #809
/*     */     //   Java source line #257	-> byte code offset #814
/*     */     //   Java source line #246	-> byte code offset #819
/*     */     //   Java source line #262	-> byte code offset #830
/*     */     //   Java source line #263	-> byte code offset #835
/*     */     //   Java source line #264	-> byte code offset #852
/*     */     //   Java source line #265	-> byte code offset #861
/*     */     //   Java source line #266	-> byte code offset #870
/*     */     //   Java source line #267	-> byte code offset #879
/*     */     //   Java source line #268	-> byte code offset #888
/*     */     //   Java source line #269	-> byte code offset #905
/*     */     //   Java source line #270	-> byte code offset #914
/*     */     //   Java source line #271	-> byte code offset #920
/*     */     //   Java source line #272	-> byte code offset #929
/*     */     //   Java source line #273	-> byte code offset #932
/*     */     //   Java source line #275	-> byte code offset #941
/*     */     //   Java source line #276	-> byte code offset #958
/*     */     //   Java source line #277	-> byte code offset #967
/*     */     //   Java source line #278	-> byte code offset #974
/*     */     //   Java source line #279	-> byte code offset #978
/*     */     //   Java source line #280	-> byte code offset #994
/*     */     //   Java source line #281	-> byte code offset #1007
/*     */     //   Java source line #282	-> byte code offset #1018
/*     */     //   Java source line #283	-> byte code offset #1023
/*     */     //   Java source line #284	-> byte code offset #1026
/*     */     //   Java source line #286	-> byte code offset #1036
/*     */     //   Java source line #287	-> byte code offset #1040
/*     */     //   Java source line #288	-> byte code offset #1049
/*     */     //   Java source line #296	-> byte code offset #1075
/*     */     //   Java source line #297	-> byte code offset #1081
/*     */     //   Java source line #289	-> byte code offset #1089
/*     */     //   Java source line #290	-> byte code offset #1090
/*     */     //   Java source line #291	-> byte code offset #1093
/*     */     //   Java source line #292	-> byte code offset #1099
/*     */     //   Java source line #296	-> byte code offset #1125
/*     */     //   Java source line #297	-> byte code offset #1131
/*     */     //   Java source line #294	-> byte code offset #1139
/*     */     //   Java source line #296	-> byte code offset #1141
/*     */     //   Java source line #297	-> byte code offset #1147
/*     */     //   Java source line #299	-> byte code offset #1152
/*     */     //   Java source line #296	-> byte code offset #1155
/*     */     //   Java source line #297	-> byte code offset #1161
/*     */     //   Java source line #300	-> byte code offset #1166
/*     */     //   Java source line #193	-> byte code offset #1172
/*     */     // Local variable table:
/*     */     //   start	length	slot	name	signature
/*     */     //   0	1175	0	args	String[]
/*     */     //   15	1012	1	scli	SQLCli
/*     */     //   33	324	2	br	java.io.BufferedReader
/*     */     //   89	18	3	credentials	String[]
/*     */     //   123	23	3	e	SQLException
/*     */     //   246	2	3	e	java.io.IOException
/*     */     //   267	62	3	useddb	ResultSet
/*     */     //   1039	24	3	e	java.io.IOException
/*     */     //   1089	24	3	e	SQLException
/*     */     //   176	3	4	e2	InterruptedException
/*     */     //   223	12	4	e1	java.io.IOException
/*     */     //   360	671	4	cmd	String
/*     */     //   433	35	5	e	java.util.Map.Entry<String, String>
/*     */     //   532	36	5	credentials	String[]
/*     */     //   585	24	5	sqle	SQLException
/*     */     //   722	62	5	sCurrentLine	String
/*     */     //   825	3	5	sCurrentLine	String
/*     */     //   1016	3	5	rs	ResultSet
/*     */     //   418	69	6	localIterator	java.util.Iterator
/*     */     //   645	163	6	concate	String
/*     */     //   666	97	7	parms	String[]
/*     */     //   686	145	8	fbr	java.io.BufferedReader
/*     */     //   803	12	9	trs	ResultSet
/*     */     //   1139	14	10	localObject	Object
/*     */     //   1084	1	11	localInterruptedException1	InterruptedException
/*     */     //   1134	1	11	localInterruptedException2	InterruptedException
/*     */     //   1150	1	11	localInterruptedException3	InterruptedException
/*     */     //   1164	1	11	localInterruptedException4	InterruptedException
/*     */     // Exception table:
/*     */     //   from	to	target	type
/*     */     //   37	120	123	java/sql/SQLException
/*     */     //   167	173	176	java/lang/InterruptedException
/*     */     //   192	220	223	java/io/IOException
/*     */     //   37	120	246	java/io/IOException
/*     */     //   513	582	585	java/sql/SQLException
/*     */     //   251	1036	1039	java/io/IOException
/*     */     //   1075	1081	1084	java/lang/InterruptedException
/*     */     //   251	1036	1089	java/sql/SQLException
/*     */     //   1125	1131	1134	java/lang/InterruptedException
/*     */     //   251	1075	1139	finally
/*     */     //   1089	1125	1139	finally
/*     */     //   1141	1147	1150	java/lang/InterruptedException
/*     */     //   1155	1161	1164	java/lang/InterruptedException
/*     */   }
/*     */ }


/* Location:              /home/coro/GitRepo/SQL_Cli.jar!/at/coro/client/SQLCli.class
 * Java compiler version: 8 (52.0)
 * JD-Core Version:       0.7.1
 */